{
  "timestamp": "2025-11-07T17:25:44.440242",
  "accelerometer": {
    "x": 0.16519992053508759,
    "y": 0.11971008777618408,
    "z": 10.163386344909668
  },
  "gyroscope": {
    "x": 0,
    "y": 0.000532632227987051,
    "z": 0
  },
  "magnetometer": {
    "x": 17.96875,
    "y": -69.23828125,
    "z": -224.0234375
  },
  "gps": {
    "latitude": 12.8655631,
    "longitude": 74.9243939,
    "altitude": -71.20000457763672,
    "speed": 1.0380266904830933,
    "accuracy": 45.75
  },
  "proximity": null,
  "ambientLight": 229,
  "pressure": null
}